[{"id": 13, "data": "29/10/2023 17:00", "confirmado": true, "id_cliente": 5, "id_servico": 2}, {"id": 14, "data": "29/10/2023 17:00", "confirmado": true, "id_cliente": 5, "id_servico": 2}, {"id": 17, "data": "17/10/2033 17:30", "confirmado": true, "id_cliente": "micaeelelleleee", "id_servico": "Lavagem Simples"}, {"id": 18, "data": "17/12/2020 17:50", "confirmado": true, "id_cliente": "reff", "id_servico": "Lavagem Simples"}, {"id": 19, "data": "17/12/2023 17:20", "confirmado": true, "id_cliente": "reff", "id_servico": "Lavagem Completa"}]